{
    "name": "free-programming-books-zh_CN",
    "stars": 116286,
    "contributors": [
        "justjavac",
        "spacewander",
        "hacpai",
        "hoosin",
        "wizardforcel",
        "Cedaric",
        "qha0731",
        "SDLyu",
        "wangminli",
        "lk375273991",
        "chencl",
        "myd7349",
        "theJian",
        "ReadmeCritic",
        "phodal",
        "ywfwj2008",
        "shidephen",
        "0532",
        "linkgod",
        "howiefh",
        "Jancd",
        "Yixiaohan",
        "ksky521",
        "wangjiezhe",
        "vforbox",
        "maguowei",
        "hacke2",
        "zombie110year",
        "Mooophy",
        "xuxiaodong",
        "dgeibi",
        "lzufalcon",
        "ztmark",
        "Liam0205",
        "Go7hic",
        "flyhigher139",
        "dragonhnd",
        "L-Jovi",
        "lkxiaolou",
        "Adherentman",
        "muxik",
        "ph87",
        "startalks",
        "time-river",
        "tsstss123",
        "unityoxb",
        "vansteki",
        "kelubo",
        "Ljhero",
        "keelii",
        "huguangju",
        "yunkaiyueming",
        "ghostsf",
        "feythin",
        "cos800",
        "chancyWu",
        "callinglove",
        "caimaoy",
        "hbzs",
        "ThisisGame",
        "lfzm",
        "Haceau-Zoac",
        "imba-tjd",
        "jysperm",
        "loocao",
        "QianMo",
        "Montia37",
        "lichunqiang",
        "me115",
        "zhou-yg",
        "Flowerowl",
        "yuche",
        "yeshan333",
        "xiaoweiChen",
        "wwj718",
        "wwek",
        "wuqinqiang",
        "withwind93",
        "dinglixiang",
        "liuqun",
        "lingcoder",
        "Lich2013",
        "kungkao",
        "KevinHu-1024",
        "kxxoling",
        "AICodeHunt",
        "2dxgujun",
        "JuanitoFatas",
        "sjsdfg",
        "zenghongtu",
        "ylvict",
        "Hawstein",
        "stacklens",
        "chen56",
        "kingofctrl",
        "Blyth0He",
        "qddegtya",
        "AlanViast",
        "bzy-nya",
        "bolasblack",
        "wcpsoft",
        "hellokaton",
        "awesome-bot",
        "waylau",
        "TuringZhu",
        "gittower-moved",
        "zhangtianle",
        "Binrun",
        "Sheng14",
        "dofy",
        "wuzhouhui",
        "ruchee",
        "RobertHoffman",
        "gmszone",
        "izmntuk",
        "mortonfox",
        "Michael18811380328",
        "JMbaozi"
    ],
    "license": "GNU General Public License v3.0",
    "topics": [
        "android",
        "angular",
        "books",
        "free",
        "ios",
        "javascript",
        "kotlin",
        "pdf",
        "programming",
        "python",
        "react",
        "react-native",
        "swift",
        "vue"
    ],
    "releases": [
        "3.0",
        "v2.0",
        "v1.0"
    ]
}